tinyioc/__init__.py
tinyioc/container.py
tinyioc/decorators.py
tinyioc/helpers.py
tinyioc/ioc_exception.py
tinyioc/service_entry.py
tinyioc/types.py
tinyioc/module/__init__.py
tinyioc/module/decorators.py
tinyioc/module/module.py
tinyioc/module/provide.py
tinyioc-0.1.4.dist-info/LICENSE
tinyioc-0.1.4.dist-info/METADATA
tinyioc-0.1.4.dist-info/WHEEL
tinyioc-0.1.4.dist-info/top_level.txt
tinyioc-0.1.4.dist-info/RECORD
