Metadata-Version: 2.1
Name: tinyioc
Version: 0.1.4
Author-email: Paolo Infante <info@paoloinfante.it>
License: MIT License
Project-URL: Homepage, https://github.com/paolo-projects/tinyioc
Keywords: dependency,injection,ioc,inversion,control
License-File: LICENSE
